ABC/__init__.py
ABC/data.py
ABC/model.py
ABC/results.py
ABC/utils.py
ABC/models/MLTC_atomic_hyp_mult.stan
abc_network-0.1.3.dist-info/LICENSE
abc_network-0.1.3.dist-info/METADATA
abc_network-0.1.3.dist-info/WHEEL
abc_network-0.1.3.dist-info/entry_points.txt
abc_network-0.1.3.dist-info/top_level.txt
abc_network-0.1.3.dist-info/RECORD
