Metadata-Version: 2.1
Name: abc_network
Version: 0.1.3
Summary: This package provides code linked to the paper "Multimorbidity analysis with low condition counts: a robust Bayesian approach for small but important subgroups" <https://authors.elsevier.com/sd/article/S2352396424001166>.
Home-page: https://github.com/Juillermo/ABC.git
Author: Guillermo Romero Moreno
Author-email: Guillermo.RomeroMoreno@ed.ac.uk
License: GNU GENERAL PUBLIC LICENSE
Keywords: Bayesian,Multimorbidity
Classifier: Programming Language :: Python :: 3
Classifier: Operating System :: OS Independent
License-File: LICENSE
Requires-Dist: numpy
Requires-Dist: scipy
Requires-Dist: pandas
Requires-Dist: matplotlib
Requires-Dist: seaborn
Requires-Dist: networkx
Requires-Dist: bokeh ==3.3.0
Requires-Dist: cmdstanpy
Requires-Dist: jupyter
Requires-Dist: ucimlrepo
